{"_via_settings":{"ui":{"annotation_editor_height":25,"annotation_editor_fontsize":0.8,"leftsidebar_width":18,"image_grid":{"img_height":80,"rshape_fill":"none","rshape_fill_opacity":0.3,"rshape_stroke":"yellow","rshape_stroke_width":2,"show_region_shape":true,"show_image_policy":"all"},"image":{"region_label":"__via_region_id__","region_color":"__via_default_region_color__","region_label_font":"10px Sans","on_image_annotation_editor_placement":"NEAR_REGION"}},"core":{"buffer_size":18,"filepath":{},"default_filepath":""},"project":{"name":"via_project_20Feb2022_11h20m"}},"_via_img_metadata":{"Capture15.JPG376837":{"filename":"Capture15.JPG","size":376837,"regions":[{"shape_attributes":{"name":"polygon","all_points_x":[1052,1047,1069,1081,1078,1078,1081,1078,1078,1078,1074],"all_points_y":[561,578,582,576,552,554,561,558,556,552,554]},"region_attributes":{"Trash":"trashbag"}},{"shape_attributes":{"name":"polygon","all_points_x":[806,833,836,814],"all_points_y":[590,594,588,580]},"region_attributes":{"Trash":"plastic bottle"}},{"shape_attributes":{"name":"polygon","all_points_x":[651,647,648,659,659,655],"all_points_y":[618,626,626,624,622,620]},"region_attributes":{"Trash":"cardboard"}},{"shape_attributes":{"name":"polygon","all_points_x":[657,660,664,665,663,660,658],"all_points_y":[593,590,590,594,598,598,595]},"region_attributes":{"Trash":"cardboard"}}],"file_attributes":{}},"Capture.JPG396116":{"filename":"Capture.JPG","size":396116,"regions":[{"shape_attributes":{"name":"polygon","all_points_x":[746,746,754,762,767,767,763,759,757,754,753],"all_points_y":[733,741,743,743,740,736,735,738,735,730,732]},"region_attributes":{"Trash":"trashbag"}},{"shape_attributes":{"name":"polygon","all_points_x":[802,802,812,815,812],"all_points_y":[738,741,742,740,737]},"region_attributes":{"Trash":"paper trash"}},{"shape_attributes":{"name":"polygon","all_points_x":[847,858,858,853,846],"all_points_y":[735,735,740,740,737]},"region_attributes":{"Trash":"paper trash"}}],"file_attributes":{}},"Capture2.JPG461489":{"filename":"Capture2.JPG","size":461489,"regions":[{"shape_attributes":{"name":"polygon","all_points_x":[1308,1307,1311,1313,1313,1311],"all_points_y":[651,658,660,658,653,651]},"region_attributes":{"Trash":"plastic bottle"}},{"shape_attributes":{"name":"polygon","all_points_x":[1361,1360,1365,1368,1366,1363],"all_points_y":[651,655,657,653,649,649]},"region_attributes":{"Trash":"plastic bottle"}},{"shape_attributes":{"name":"polygon","all_points_x":[1510,1508,1528,1540,1541],"all_points_y":[726,736,744,740,737]},"region_attributes":{"Trash":"paper trash"}}],"file_attributes":{}},"Capture3.JPG447144":{"filename":"Capture3.JPG","size":447144,"regions":[{"shape_attributes":{"name":"polygon","all_points_x":[712,700,697,707,713,717],"all_points_y":[650,655,659,659,659,656]},"region_attributes":{"Trash":"trashbag"}},{"shape_attributes":{"name":"polygon","all_points_x":[1206,1224,1253,1238],"all_points_y":[709,723,719,706]},"region_attributes":{"Trash":"cardboard"}},{"shape_attributes":{"name":"polygon","all_points_x":[1259,1256,1260,1277,1274],"all_points_y":[706,714,717,709,705]},"region_attributes":{"Trash":"paper trash"}}],"file_attributes":{}},"Capture4.JPG453850":{"filename":"Capture4.JPG","size":453850,"regions":[{"shape_attributes":{"name":"polygon","all_points_x":[962,962,970,980,996,999,979,986,982,974],"all_points_y":[680,693,696,694,689,674,673,680,682,679]},"region_attributes":{"Trash":"trashbag"}}],"file_attributes":{}},"Capture5.JPG399511":{"filename":"Capture5.JPG","size":399511,"regions":[{"shape_attributes":{"name":"polygon","all_points_x":[863,878,884,882,866],"all_points_y":[788,780,792,806,805]},"region_attributes":{"Trash":"trashbag"}}],"file_attributes":{}},"Capture6.JPG350815":{"filename":"Capture6.JPG","size":350815,"regions":[{"shape_attributes":{"name":"polygon","all_points_x":[98,93,129,142,143,140,135],"all_points_y":[705,721,735,728,718,711,708]},"region_attributes":{"Trash":"paper bag"}},{"shape_attributes":{"name":"polygon","all_points_x":[1501,1492,1493,1512,1517,1513,1509],"all_points_y":[760,763,766,767,763,759,754]},"region_attributes":{"Trash":"paper bag"}},{"shape_attributes":{"name":"polygon","all_points_x":[1070,1074,1080,1084,1085,1083,1078],"all_points_y":[782,786,788,786,780,777,777]},"region_attributes":{"Trash":"paper bag"}}],"file_attributes":{}},"Capture7.JPG433448":{"filename":"Capture7.JPG","size":433448,"regions":[{"shape_attributes":{"name":"polygon","all_points_x":[621,622,632,636,642,640],"all_points_y":[747,764,766,763,761,746]},"region_attributes":{"Trash":"paper bag"}}],"file_attributes":{}},"Capture8.JPG393542":{"filename":"Capture8.JPG","size":393542,"regions":[{"shape_attributes":{"name":"polygon","all_points_x":[788,780,793,797,792],"all_points_y":[505,530,540,536,521]},"region_attributes":{"Trash":"Aluminium can"}},{"shape_attributes":{"name":"polygon","all_points_x":[876,888,900,912,898,891,887,879,880,874],"all_points_y":[543,541,543,552,557,553,556,552,550,547]},"region_attributes":{"Trash":"paper trash"}},{"shape_attributes":{"name":"polygon","all_points_x":[842,864,875,876,865,854,839],"all_points_y":[494,505,508,514,514,515,502]},"region_attributes":{"Trash":"paper trash"}},{"shape_attributes":{"name":"polygon","all_points_x":[858,856,886,900,890,874],"all_points_y":[585,593,600,590,581,586]},"region_attributes":{"Trash":"paper trash"}}],"file_attributes":{}},"Capture9.JPG349492":{"filename":"Capture9.JPG","size":349492,"regions":[{"shape_attributes":{"name":"polygon","all_points_x":[1687,1656,1661,1692,1722,1716,1705,1702],"all_points_y":[705,722,732,742,740,723,722,712]},"region_attributes":{"Trash":"trashbag"}}],"file_attributes":{}},"Capture10.JPG341413":{"filename":"Capture10.JPG","size":341413,"regions":[{"shape_attributes":{"name":"polygon","all_points_x":[435,452,447,423,399],"all_points_y":[802,813,829,837,825]},"region_attributes":{"Trash":"paper trash"}},{"shape_attributes":{"name":"polygon","all_points_x":[264,257,296,310],"all_points_y":[290,310,319,290]},"region_attributes":{"Trash":"paper trash"}}],"file_attributes":{}},"Capture11.JPG268013":{"filename":"Capture11.JPG","size":268013,"regions":[{"shape_attributes":{"name":"polygon","all_points_x":[547,542,580,589,587],"all_points_y":[740,754,757,751,739]},"region_attributes":{"Trash":"Aluminium can"}},{"shape_attributes":{"name":"polygon","all_points_x":[1456,1444,1453,1475,1463],"all_points_y":[751,759,767,764,753]},"region_attributes":{"Trash":"paper trash"}}],"file_attributes":{}},"Capture12.JPG279937":{"filename":"Capture12.JPG","size":279937,"regions":[{"shape_attributes":{"name":"polygon","all_points_x":[1307,1172,1221,1322,1371,1385,1421],"all_points_y":[531,607,643,649,632,592,585]},"region_attributes":{"Trash":"cardboard"}},{"shape_attributes":{"name":"polygon","all_points_x":[1391,1371,1378,1391,1396,1405],"all_points_y":[418,437,461,461,448,443]},"region_attributes":{"Trash":"paper trash"}},{"shape_attributes":{"name":"polygon","all_points_x":[709,695,754,770],"all_points_y":[743,781,777,743]},"region_attributes":{"Trash":"paper trash"}}],"file_attributes":{}},"Capture13.JPG442367":{"filename":"Capture13.JPG","size":442367,"regions":[],"file_attributes":{}},"Capture14.JPG414624":{"filename":"Capture14.JPG","size":414624,"regions":[{"shape_attributes":{"name":"polygon","all_points_x":[949,939,947,970,962],"all_points_y":[831,841,850,840,835]},"region_attributes":{"Trash":"paper trash"}},{"shape_attributes":{"name":"polygon","all_points_x":[1065,1084,1073,1065,1058],"all_points_y":[817,811,804,803,809]},"region_attributes":{"Trash":"paper trash"}},{"shape_attributes":{"name":"polygon","all_points_x":[1086,1116,1108,1093,1088,1080],"all_points_y":[828,825,819,815,809,819]},"region_attributes":{"Trash":"paper trash"}},{"shape_attributes":{"name":"polygon","all_points_x":[970,1001,995,973,971,966],"all_points_y":[860,857,848,839,843,845]},"region_attributes":{"Trash":"paper trash"}},{"shape_attributes":{"name":"polygon","all_points_x":[706,700,720,729,722,718,713],"all_points_y":[455,467,466,464,461,461,461]},"region_attributes":{"Trash":"trashbag"}}],"file_attributes":{}},"HairitageFamilySalon_Street.JPG205548":{"filename":"HairitageFamilySalon_Street.JPG","size":205548,"regions":[{"shape_attributes":{"name":"polygon","all_points_x":[551,555,568,565],"all_points_y":[784,789,784,778]},"region_attributes":{"Trash":"paper trash"}}],"file_attributes":{}},"Main Street.JPG272891":{"filename":"Main Street.JPG","size":272891,"regions":[],"file_attributes":{}},"MissionRoad.JPG378616":{"filename":"MissionRoad.JPG","size":378616,"regions":[{"shape_attributes":{"name":"polygon","all_points_x":[699,699,707,712],"all_points_y":[637,640,639,636]},"region_attributes":{"Trash":"plastic bottle"}}],"file_attributes":{}}},"_via_attributes":{"region":{"Trash":{"type":"dropdown","description":"","options":{"trashbag":"","cardboard":"","plastic bottle":"","paper bag":"","paper trash":"","Aluminium can":""},"default_options":{"trashbag":true}}},"file":{}},"_via_data_format_version":"2.0.10","_via_image_id_list":["Capture15.JPG376837","Capture.JPG396116","Capture2.JPG461489","Capture3.JPG447144","Capture4.JPG453850","Capture5.JPG399511","Capture6.JPG350815","Capture7.JPG433448","Capture8.JPG393542","Capture9.JPG349492","Capture10.JPG341413","Capture11.JPG268013","Capture12.JPG279937","Capture13.JPG442367","Capture14.JPG414624","HairitageFamilySalon_Street.JPG205548","Main Street.JPG272891","MissionRoad.JPG378616"]}